liveeo/perfect_utils/__init__.py
liveeo/perfect_utils/dummy.py
liveo_perfect_utils-2.8.8.dist-info/LICENSE.txt
liveo_perfect_utils-2.8.8.dist-info/METADATA
liveo_perfect_utils-2.8.8.dist-info/WHEEL
liveo_perfect_utils-2.8.8.dist-info/RECORD
